setup.py
gaussbino_distributions/Binomialdistribution.py
gaussbino_distributions/Gaussiandistribution.py
gaussbino_distributions/Generaldistribution.py
gaussbino_distributions/__init__.py
gaussbino_distributions.egg-info/PKG-INFO
gaussbino_distributions.egg-info/SOURCES.txt
gaussbino_distributions.egg-info/dependency_links.txt
gaussbino_distributions.egg-info/not-zip-safe
gaussbino_distributions.egg-info/top_level.txt