Metadata-Version: 1.0
Name: gaussbino-distributions
Version: 0.1
Summary: Gaussian and Binomial distributions
Home-page: UNKNOWN
Author: Tosin Fawibe
Author-email: oluwatosinfawibe@gmail.com
License: UNKNOWN
Platform: UNKNOWN
